gen_make/__init__.py
gen_make/do_makefile.py
gen_make/script.py
Gen_make-1.0.1.dist-info/LICENSE.txt
Gen_make-1.0.1.dist-info/METADATA
Gen_make-1.0.1.dist-info/WHEEL
Gen_make-1.0.1.dist-info/entry_points.txt
Gen_make-1.0.1.dist-info/top_level.txt
Gen_make-1.0.1.dist-info/RECORD
