Metadata-Version: 2.1
Name: Gen-make
Version: 1.0.1
Summary: A script generate basic Makefile
Home-page: https://github.com/Ideas100/Gen-make
Author: Pravin Raghul
Author-email: pravinraghul@gmail.com
License: MIT
Platform: UNKNOWN
Classifier: Intended Audience :: Developers
Classifier: License :: OSI Approved :: MIT License
Classifier: Programming Language :: Python :: 3.8
